_pydelatin.cpython-311-darwin.so
pydelatin/delatin.py
pydelatin/util.py
pydelatin/__init__.py
pydelatin/py.typed
pydelatin-0.3.0.dist-info/RECORD
pydelatin-0.3.0.dist-info/WHEEL
pydelatin-0.3.0.dist-info/top_level.txt
pydelatin-0.3.0.dist-info/METADATA
pydelatin-0.3.0.dist-info/licenses/LICENSE
