Metadata-Version: 2.4
Name: pydelatin
Version: 0.3.0
Summary: A wrapper for hmm
Home-page: https://github.com/kylebarron/pydelatin
Author: Kyle Barron
Author-email: kylebarron2@gmail.com
Requires-Python: >=3.9
License-File: LICENSE
Requires-Dist: numpy
Provides-Extra: test
Requires-Dist: pytest; extra == "test"
Requires-Dist: pytest-benchmark; extra == "test"
Requires-Dist: imageio; extra == "test"
Dynamic: author
Dynamic: author-email
Dynamic: description
Dynamic: description-content-type
Dynamic: home-page
Dynamic: license-file
Dynamic: provides-extra
Dynamic: requires-dist
Dynamic: requires-python
Dynamic: summary
